LICENSE
README.md
setup.py
cgi_printenv.egg-info/PKG-INFO
cgi_printenv.egg-info/SOURCES.txt
cgi_printenv.egg-info/dependency_links.txt
cgi_printenv.egg-info/entry_points.txt
cgi_printenv.egg-info/requires.txt
cgi_printenv.egg-info/top_level.txt
cgiprintenv/main.py
cgiprintenv/includes/__init__.py
cgiprintenv/includes/bot.py
cgiprintenv/includes/filereader.py
cgiprintenv/includes/scan.py
cgiprintenv/includes/writefile.py
cgiprintenv/utils/__init__.py
cgiprintenv/utils/configure.py
cgiprintenv/utils/const.py
cgiprintenv/utils/helpers.py
cgiprintenv/utils/status.py